[
  {
    "code": "29110-G2000",
    "target_url": "https://www.razoryn.co.uk/products/hyundai-ioniq-2016-2022-engine-undertray-under-cover",
    "kind": "product",
    "label": "HYUNDAI IONIQ Engine Undertray Under Cover",
    "utm_campaign": "ioniq"
  },
  {
    "code": "86511-G2000",
    "target_url": "https://www.razoryn.co.uk/products/hyundai-ioniq-2016-2019-primed-front-bumper-skin",
    "kind": "product",
    "label": "HYUNDAI IONIQ Front Bumper Skin",
    "utm_campaign": "ioniq"
  },
  {
    "code": "86563-G2050",
    "target_url": "https://www.razoryn.co.uk/products/hyundai-ioniq-2016-2021-fog-light-lamp-left-side-bezel-surround-trim",
    "kind": "product",
    "label": "HYUNDAI IONIQ Fog Light Lamp Left Side Bezel Surround Trim",
    "utm_campaign": "ioniq"
  },
  {
    "code": "86564-G2050",
    "target_url": "https://www.razoryn.co.uk/products/hyundai-ioniq-2016-2021-fog-light-lamp-right-side-bezel-surround-trim",
    "kind": "product",
    "label": "HYUNDAI IONIQ Fog Light Lamp Right Side Bezel Surround Trim",
    "utm_campaign": "ioniq"
  },
  {
    "code": "86585-G2000",
    "target_url": "https://www.razoryn.co.uk/products/hyundai-ioniq-2016-2021-front-bumper-center-upper-moulding",
    "kind": "product",
    "label": "HYUNDAI IONIQ Front Bumper Center Upper Moulding",
    "utm_campaign": "ioniq"
  },
  {
    "code": "86350-G2000",
    "target_url": "https://www.razoryn.co.uk/products/hyundai-ioniq-2016-2020-glossy-front-bumper-radiator-grille-black",
    "kind": "product",
    "label": "HYUNDAI IONIQ Front Bumper Radiator Grille Black",
    "utm_campaign": "ioniq"
  },
  {
    "code": "92207-G2000",
    "target_url": "https://www.razoryn.co.uk/products/hyundai-ioniq-2017-2019-front-daytime-running-light-left-side",
    "kind": "product",
    "label": "HYUNDAI IONIQ Front Daytime Running Light Left Side",
    "utm_campaign": "ioniq"
  },
  {
    "code": "2208-G2000",
    "target_url": "https://www.razoryn.co.uk/products/hyundai-ioniq-2017-2019-front-daytime-running-light-right-side",
    "kind": "product",
    "label": "HYUNDAI IONIQ Front Daytime Running Light Right Side",
    "utm_campaign": "ioniq"
  },
  {
    "code": "66400-G2000",
    "target_url": "https://www.razoryn.co.uk/products/hyundai-ioniq-2017-2021-primed-bonnet-hood",
    "kind": "product",
    "label": "HYUNDAI IONIQ Bonnet Hood",
    "utm_campaign": "ioniq"
  },
  {
    "code": "86560-G2100",
    "target_url": "https://www.razoryn.co.uk/products/hyundai-ioniq-2018-2023-front-bumper-lower-grille",
    "kind": "product",
    "label": "HYUNDAI IONIQ Front Bumper Lower Grille",
    "utm_campaign": "ioniq"
  },
  {
    "code": "86586-G2500",
    "target_url": "https://www.razoryn.co.uk/products/hyundai-ioniq-2020-2023-front-bumper-chrome-grille-surround",
    "kind": "product",
    "label": "HYUNDAI IONIQ Front Bumper Chrome Grille Surround",
    "utm_campaign": "ioniq"
  }
]